bullet_ur_gym_test/__init__.py
bullet_ur_gym_test/envs/__init__.py
bullet_ur_gym_test/envs/ur_env.py
bullet_ur_gym_test/envs/ur_env_goal.py
bullet_ur_gym_test-0.0.5.dist-info/LICENSE
bullet_ur_gym_test-0.0.5.dist-info/METADATA
bullet_ur_gym_test-0.0.5.dist-info/WHEEL
bullet_ur_gym_test-0.0.5.dist-info/top_level.txt
bullet_ur_gym_test-0.0.5.dist-info/RECORD
