Metadata-Version: 2.1
Name: bullet-ur-gym-test
Version: 0.0.5
Summary: An OpenAI Gym Env for UR
Home-page: https://github.com/juhk1017/gym-panda
Author: juhwakKim
Author-email: juhk1017@naver.com
License: UNKNOWN
Platform: UNKNOWN
Classifier: Programming Language :: Python :: 3
Classifier: License :: OSI Approved :: MIT License
Classifier: Operating System :: OS Independent
Requires-Python: >=3.6
Requires-Dist: gym
Requires-Dist: pybullet
Requires-Dist: numpy
